r7insights/__init__.py
r7insights/helpers.py
r7insights/metrics.py
r7insights/utils.py
r7insights-0.2.0.dist-info/METADATA
r7insights-0.2.0.dist-info/WHEEL
r7insights-0.2.0.dist-info/top_level.txt
r7insights-0.2.0.dist-info/RECORD
