Metadata-Version: 2.1
Name: r7insights
Version: 0.2.0
Summary: r7insights
Author: angela.camardella@freedamedia.com
